chipmunkdb/ChipmunkDb.py
chipmunkdb/__init__.py
chipmunkdb/base.py
chipmunkdb/config.cfg
chipmunkdb/jdbc.py
chipmunkdb/chipmunkdbapi/__init__.py
chipmunkdb/chipmunkdbapi/_chipmunkdbapi.py
chipmunkdb/chipmunkdbapi/api_exceptions.py
chipmunkdb/chipmunkdbapi/api_globals.py
chipmunkdb_python_client-2.0.22.dist-info/LICENSE
chipmunkdb_python_client-2.0.22.dist-info/METADATA
chipmunkdb_python_client-2.0.22.dist-info/WHEEL
chipmunkdb_python_client-2.0.22.dist-info/entry_points.txt
chipmunkdb_python_client-2.0.22.dist-info/top_level.txt
chipmunkdb_python_client-2.0.22.dist-info/RECORD
