Metadata-Version: 2.1
Name: chipmunkdb_python_client
Version: 2.0.22
Summary: Read and Write Dataframes and Data to a chipmunkdb
Home-page: https://gitlab.com/coindeck/chipmunkdb-python-client
Author: coindeck
Author-email: donnercody86@gmail.com
License: MIT
Classifier: License :: OSI Approved :: MIT License
Classifier: Programming Language :: Python
Classifier: Programming Language :: Python :: 2
Classifier: Programming Language :: Python :: 3
License-File: LICENSE
Requires-Dist: requests
Requires-Dist: sqlalchemy
Requires-Dist: pandas
Requires-Dist: influxdb
Requires-Dist: ijson
Requires-Dist: importlib-resources
Requires-Dist: typing
